xbim/__init__.py
xbim/core/__init__.py
xbim/core/convert.py
xbim/frame/shapes/__init__.py
xcsi/__init__.py
xcsi/__main__.py
xcsi/assembly.py
xcsi/job.py
xcsi/metrics.py
xcsi/names.py
xcsi/options.py
xcsi/rha.py
xcsi/_assembly/__init__.py
xcsi/_assembly/frame.py
xcsi/_instance/__init__.py
xcsi/_instance/_shell.py
xcsi/_instance/link.py
xcsi/_io/__init__.py
xcsi/_io/_json.py
xcsi/_loading/__init__.py
xcsi/csi/__init__.py
xcsi/csi/_material.py
xcsi/csi/_section.py
xcsi/csi/_solid.py
xcsi/csi/analysis.py
xcsi/csi/bridge.py
xcsi/csi/config.py
xcsi/csi/parse.py
xcsi/csi/point.py
xcsi/csi/schema.py
xcsi/csi/tables.py
xcsi/csi/utility.py
xcsi/csi/_frame/__init__.py
xcsi/csi/_frame/outlines.py
xcsi/csi/_frame/section.py
xcsi-0.0.6.dist-info/licenses/LICENSE
xcsi-0.0.6.dist-info/METADATA
xcsi-0.0.6.dist-info/WHEEL
xcsi-0.0.6.dist-info/entry_points.txt
xcsi-0.0.6.dist-info/top_level.txt
xcsi-0.0.6.dist-info/RECORD
