Metadata-Version: 2.4
Name: xcsi
Version: 0.0.6
Summary: Build finite element models for OpenSees and Xara from CSiBridge and SAP2000 input files.
Author-email: Pacific Earthquake Engineering Research Center <184699016+peer-open-source@users.noreply.github.com>, Issac Pang <101420268+issacpang@users.noreply.github.com>, "Claudio M. Perez" <50180406+claudioperez@users.noreply.github.com>
Project-URL: Home, https://gallery.stairlab.io
Keywords: bridges,finite-element-analysis,structural-analysis,seismic,earthquake-engineering
Classifier: Development Status :: 2 - Pre-Alpha
Classifier: Intended Audience :: Science/Research
Classifier: Intended Audience :: Developers
Classifier: Topic :: Software Development
Classifier: Topic :: Scientific/Engineering
Classifier: Programming Language :: Python
Classifier: Programming Language :: Python :: 3
Classifier: Programming Language :: Python :: 3.7
Classifier: Programming Language :: Python :: 3.8
Classifier: Programming Language :: Python :: 3.9
Classifier: Programming Language :: Python :: 3.10
Classifier: Programming Language :: Python :: 3.11
Classifier: Programming Language :: Python :: 3.12
Classifier: Programming Language :: Python :: 3 :: Only
Classifier: Operating System :: Microsoft :: Windows
Classifier: Operating System :: POSIX
Classifier: Operating System :: Unix
Classifier: Operating System :: MacOS
License-File: LICENSE
Requires-Dist: xara>=0.0.15
Requires-Dist: veux>=0.0.41
Requires-Dist: numpy
Requires-Dist: genson
Requires-Dist: opensees>=0.1.0
Requires-Dist: xsection>=0.0.20
Provides-Extra: dev
Requires-Dist: pytest; extra == "dev"
Dynamic: license-file
